screen_recorder/__init__.py
screen_recorder/_ffmpeg.py
screen_recorder/audio.py
screen_recorder/exceptions.py
screen_recorder/ffmpeg.exe
screen_recorder/recorder.py
screen_recorder/video.py
screen_recorder_python-1.2.5.dist-info/LICENCE.txt
screen_recorder_python-1.2.5.dist-info/METADATA
screen_recorder_python-1.2.5.dist-info/WHEEL
screen_recorder_python-1.2.5.dist-info/top_level.txt
screen_recorder_python-1.2.5.dist-info/RECORD
