Metadata-Version: 2.1
Name: screen-recorder-python
Version: 1.2.5
Summary: A simple screen recorder package for python
Home-page: https://github.com/Pranav433/screen_recorder
Author: Pranav Parashar
Author-email: krish420360@gmail.com
License: MIT
Keywords: screen recorder
Platform: UNKNOWN
Classifier: Development Status :: 5 - Production/Stable
Classifier: Intended Audience :: Education
Classifier: Operating System :: Microsoft :: Windows :: Windows 10
Classifier: License :: OSI Approved :: MIT License
Classifier: Programming Language :: Python :: 3
Requires-Dist: cffi (==1.14.5)
Requires-Dist: future (==0.18.2)
Requires-Dist: MouseInfo (==0.1.3)
Requires-Dist: numpy (==1.20.1)
Requires-Dist: opencv-python (==4.5.1.48)
Requires-Dist: Pillow (==8.1.2)
Requires-Dist: PyAutoGUI (==0.9.52)
Requires-Dist: pycparser (==2.20)
Requires-Dist: PyGetWindow (==0.0.9)
Requires-Dist: PyMsgBox (==1.0.9)
Requires-Dist: pyperclip (==1.8.2)
Requires-Dist: PyRect (==0.1.4)
Requires-Dist: PyScreeze (==0.1.26)
Requires-Dist: PyTweening (==1.0.3)
Requires-Dist: sounddevice (==0.4.1)
Requires-Dist: SoundFile (==0.10.3.post1)
